tianshou/__init__.py
tianshou/config.py
tianshou/data/__init__.py
tianshou/data/batch.py
tianshou/data/buffer/__init__.py
tianshou/data/buffer/base.py
tianshou/data/buffer/cached.py
tianshou/data/buffer/her.py
tianshou/data/buffer/manager.py
tianshou/data/buffer/prio.py
tianshou/data/buffer/vecbuf.py
tianshou/data/collector.py
tianshou/data/stats.py
tianshou/data/types.py
tianshou/data/utils/__init__.py
tianshou/data/utils/converter.py
tianshou/data/utils/segtree.py
tianshou/env/__init__.py
tianshou/env/gym_wrappers.py
tianshou/env/pettingzoo_env.py
tianshou/env/utils.py
tianshou/env/venv_wrappers.py
tianshou/env/venvs.py
tianshou/env/worker/__init__.py
tianshou/env/worker/base.py
tianshou/env/worker/dummy.py
tianshou/env/worker/ray.py
tianshou/env/worker/subproc.py
tianshou/evaluation/__init__.py
tianshou/evaluation/launcher.py
tianshou/evaluation/rliable_evaluation_hl.py
tianshou/exploration/__init__.py
tianshou/exploration/random.py
tianshou/highlevel/__init__.py
tianshou/highlevel/agent.py
tianshou/highlevel/config.py
tianshou/highlevel/env.py
tianshou/highlevel/experiment.py
tianshou/highlevel/logger.py
tianshou/highlevel/module/__init__.py
tianshou/highlevel/module/actor.py
tianshou/highlevel/module/core.py
tianshou/highlevel/module/critic.py
tianshou/highlevel/module/intermediate.py
tianshou/highlevel/module/module_opt.py
tianshou/highlevel/module/special.py
tianshou/highlevel/optim.py
tianshou/highlevel/params/__init__.py
tianshou/highlevel/params/alpha.py
tianshou/highlevel/params/dist_fn.py
tianshou/highlevel/params/env_param.py
tianshou/highlevel/params/lr_scheduler.py
tianshou/highlevel/params/noise.py
tianshou/highlevel/params/policy_params.py
tianshou/highlevel/params/policy_wrapper.py
tianshou/highlevel/persistence.py
tianshou/highlevel/trainer.py
tianshou/highlevel/world.py
tianshou/policy/__init__.py
tianshou/policy/base.py
tianshou/policy/imitation/__init__.py
tianshou/policy/imitation/base.py
tianshou/policy/imitation/bcq.py
tianshou-1.2.0.dist-info/LICENSE
tianshou-1.2.0.dist-info/METADATA
tianshou-1.2.0.dist-info/WHEEL
tianshou-1.2.0.dist-info/RECORD
