Metadata-Version: 2.3
Name: tianshou
Version: 1.2.0
Summary: A Library for Deep Reinforcement Learning
License: MIT
Author: TSAIL
Author-email: trinkle23897@gmail.com
Requires-Python: >=3.11,<4.0
Classifier: Development Status :: 4 - Beta
Classifier: Intended Audience :: Science/Research
Classifier: License :: OSI Approved :: MIT License
Classifier: Programming Language :: Python :: 3
Classifier: Programming Language :: Python :: 3.11
Classifier: Programming Language :: Python :: 3.12
Classifier: Programming Language :: Python :: 3.13
Classifier: Topic :: Scientific/Engineering :: Artificial Intelligence
Classifier: Topic :: Software Development :: Libraries :: Python Modules
Provides-Extra: argparse
Provides-Extra: atari
Provides-Extra: box2d
Provides-Extra: classic-control
Provides-Extra: envpool
Provides-Extra: eval
Provides-Extra: mujoco
Provides-Extra: mujoco-py
Provides-Extra: pybullet
Provides-Extra: robotics
Provides-Extra: vizdoom
Requires-Dist: ale-py (>=0.8.1,<0.9.0) ; extra == "atari"
Requires-Dist: autorom[accept-rom-license] (>=0.4.2,<0.5.0) ; extra == "atari"
Requires-Dist: box2d_py (==2.3.5) ; extra == "box2d"
Requires-Dist: cython (>=0.27.2) ; extra == "mujoco-py"
Requires-Dist: deepdiff (>=7.0.1,<8.0.0)
Requires-Dist: docstring-parser (>=0.15,<0.16) ; extra == "argparse" or extra == "eval"
Requires-Dist: envpool (>=0.8.2,<0.9.0) ; (sys_platform != "darwin") and (extra == "envpool")
Requires-Dist: gymnasium (>=0.28.0,<0.29.0)
Requires-Dist: gymnasium-robotics ; extra == "robotics"
Requires-Dist: h5py (>=3.9.0,<4.0.0)
Requires-Dist: imageio (>=2.14.1) ; extra == "mujoco"
Requires-Dist: joblib ; extra == "eval"
Requires-Dist: jsonargparse (>=4.24.1,<5.0.0) ; extra == "argparse" or extra == "eval"
Requires-Dist: matplotlib (>=3.0.0)
Requires-Dist: mujoco (>=2.1.5,<3) ; extra == "mujoco"
Requires-Dist: mujoco-py (>=2.1,<2.2) ; extra == "mujoco-py"
Requires-Dist: numba (>=0.60.0)
Requires-Dist: numpy (>=1,<2)
Requires-Dist: opencv_python ; extra == "atari"
Requires-Dist: overrides (>=7.4.0,<8.0.0)
Requires-Dist: packaging
Requires-Dist: pandas (>=2.0.0)
Requires-Dist: pettingzoo (>=1.22,<2.0)
Requires-Dist: pybullet ; extra == "pybullet"
Requires-Dist: pygame (>=2.1.3) ; extra == "box2d" or extra == "classic-control"
Requires-Dist: rliable (==1.2.0) ; extra == "eval"
Requires-Dist: scipy ; extra == "eval"
Requires-Dist: sensai-utils (>=1.4.0,<2.0.0)
Requires-Dist: shimmy (>=0.1.0,<1.0) ; extra == "atari"
Requires-Dist: swig (==4.*) ; extra == "box2d"
Requires-Dist: tensorboard (>=2.5.0,<3.0.0)
Requires-Dist: torch (>=2.0.0,<3.0.0,!=2.0.1,!=2.1.0)
Requires-Dist: tqdm
Requires-Dist: virtualenv (<20.16.4) ; sys_platform == "win32"
Requires-Dist: virtualenv (>=20.4.3,<21.0.0,!=20.4.5,!=20.4.6)
Requires-Dist: vizdoom ; extra == "vizdoom"
Project-URL: Homepage, https://github.com/thu-ml/tianshou
